{
  "schema_version": 2,
  "synthetic_only": true,
  "seed": 22589824271730501,
  "duration_h": 9.0,
  "speed_kn": 6.0,
  "distance_km": 100.0079136,
  "gps_loss_h": 2.0,
  "ephemeris_cache_h": 0.0,
  "integration_step_s": 1,
  "hard_6h": {
    "doppler_available_until_h": 6.0,
    "accepted_doppler_updates": 1083,
    "rejected_doppler_updates": 540,
    "final_position_error_m": 3636.7505858303543,
    "position_class": "dead-reckoning (>1 NM error)"
  },
  "graduated_30h": {
    "doppler_available_until_h": 9.0,
    "accepted_doppler_updates": 1623,
    "rejected_doppler_updates": 0,
    "final_position_error_m": 1632.5819045307908,
    "position_class": "passage-held (<1 NM error)"
  },
  "caveat": "D43 applies: synthetic epoch aging aliases orbital phase and is availability evidence only, not validation of real SupGP error growth."
}